puppet/__init__.py
puppet/apiclients/__init__.py
puppet/apiclients/dogsapi.py
puppet/apiwrappers/__init__.py
puppet/apiwrappers/authenticator.py
puppet/apiwrappers/dto.py
puppet/apiwrappers/httpresponsehandler.py
puppet/apiwrappers/restapiwrappers.py
puppet/apiwrappers/serializers.py
puppet/decorators/__init__.py
puppet/decorators/debug.py
puppet/decorators/ratelimiters.py
puppet/decorators/retries.py
puppet/decorators/timeout.py
puppet/utils/__init__.py
puppet/utils/compiledregex.py
puppet/utils/dataclasstools.py
puppet/utils/loggers.py
puppet/wip/__init__.py
puppet/wip/excelworkbookextractor.py
api_puppet-0.0.42.dist-info/METADATA
api_puppet-0.0.42.dist-info/WHEEL
api_puppet-0.0.42.dist-info/top_level.txt
api_puppet-0.0.42.dist-info/RECORD
