Metadata-Version: 2.4
Name: api-puppet
Version: 0.0.42
Summary: A library to accelerate REST API clients development.
Author-email: Michaël Sauget <michaelsauget@gmail.com>
Requires-Python: >=3.7
Requires-Dist: python-dateutil
Requires-Dist: requests
